aos_prov/__init__.py
aos_prov/__main__.py
aos_prov/actions.py
aos_prov/main.py
aos_prov/commands/__init__.py
aos_prov/commands/command_provision.py
aos_prov/commands/command_vm.py
aos_prov/commands/command_vm_libvirt.py
aos_prov/commands/command_vm_multi_node.py
aos_prov/commands/command_vm_multi_node_manage.py
aos_prov/commands/download.py
aos_prov/commands/provision_v5.py
aos_prov/commands/vbox_sdk.py
aos_prov/communication/__init__.py
aos_prov/communication/cloud/__init__.py
aos_prov/communication/cloud/cloud_api.py
aos_prov/communication/unit/__init__.py
aos_prov/communication/unit/v0/__init__.py
aos_prov/communication/unit/v0/unit_communacation.py
aos_prov/communication/unit/v0/unit_communication.py
aos_prov/communication/unit/v0/generated/__init__.py
aos_prov/communication/unit/v0/generated/api_iamanager_iamanager_pb2.py
aos_prov/communication/unit/v0/generated/api_iamanager_iamanager_pb2_grpc.py
aos_prov/communication/unit/v1/__init__.py
aos_prov/communication/unit/v1/unit_communacation_v1.py
aos_prov/communication/unit/v1/unit_communication_v1.py
aos_prov/communication/unit/v1/generated/__init__.py
aos_prov/communication/unit/v1/generated/iamanagercommon_pb2.py
aos_prov/communication/unit/v1/generated/iamanagercommon_pb2_grpc.py
aos_prov/communication/unit/v1/generated/iamanagerprotected_pb2.py
aos_prov/communication/unit/v1/generated/iamanagerprotected_pb2_grpc.py
aos_prov/communication/unit/v1/generated/iamanagerpublic_pb2.py
aos_prov/communication/unit/v1/generated/iamanagerpublic_pb2_grpc.py
aos_prov/communication/unit/v2/__init__.py
aos_prov/communication/unit/v2/unit_communacation_v2.py
aos_prov/communication/unit/v2/unit_communication_v2.py
aos_prov/communication/unit/v2/generated/__init__.py
aos_prov/communication/unit/v2/generated/iamanagercommon_pb2.py
aos_prov/communication/unit/v2/generated/iamanagercommon_pb2_grpc.py
aos_prov/communication/unit/v2/generated/iamanagerprotected_pb2.py
aos_prov-5.2.0.dist-info/METADATA
aos_prov-5.2.0.dist-info/WHEEL
aos_prov-5.2.0.dist-info/entry_points.txt
aos_prov-5.2.0.dist-info/top_level.txt
aos_prov-5.2.0.dist-info/RECORD
