Metadata-Version: 2.4
Name: aos-prov
Version: 5.2.0
Summary: AosEdge Unit provisioning tool
Author: EPAM Systems
Author-email: support@aoscloud.io
License: Apache License 2.0
Platform: any
Classifier: Operating System :: OS Independent
Classifier: Programming Language :: Python :: 3
Classifier: Programming Language :: Python :: 3.7
Classifier: Programming Language :: Python :: 3.8
Classifier: Programming Language :: Python :: 3.9
Classifier: Programming Language :: Python :: 3.10
Classifier: Programming Language :: Python :: 3.11
Classifier: Programming Language :: Python :: 3.12
Requires-Python: >=3.7
Requires-Dist: aos-keys>=1.9.0b4
Requires-Dist: grpcio>=1.44.0
Requires-Dist: importlib-resources>=3.0; python_version < "3.9"
Requires-Dist: importlib-metadata==4.2.0; python_version < "3.8"
Requires-Dist: protobuf<=3.20.1,>=3.14
Requires-Dist: protobuf==3.20.*
Requires-Dist: asn1crypto>=1.4.0
Requires-Dist: rich>=10.13
Requires-Dist: semver>=3.0.2
Provides-Extra: dev
Requires-Dist: grpcio-tools~=1.34; extra == "dev"
Dynamic: author
Dynamic: author-email
Dynamic: classifier
Dynamic: description
Dynamic: description-content-type
Dynamic: license
Dynamic: platform
Dynamic: provides-extra
Dynamic: requires-dist
Dynamic: requires-python
Dynamic: summary
